README.md
setup.py
distributions_carlo/Binomialdistribution.py
distributions_carlo/Gaussiandistribution.py
distributions_carlo/Generaldistribution.py
distributions_carlo/__init__.py
distributions_carlo.egg-info/PKG-INFO
distributions_carlo.egg-info/SOURCES.txt
distributions_carlo.egg-info/dependency_links.txt
distributions_carlo.egg-info/not-zip-safe
distributions_carlo.egg-info/top_level.txt